Workbook

Sheet Assumptions
B2: Groupe Ariel — Cartridge Recycling (Mexico)
B3: Cross-border replacement / cost-savings decision. Value the project where the cash lives (pesos), translate with parity, prove currency choice does not change NPV.
B5: Investment & Equipment
B6: Initial investment — new equipment (MXN) | C6: 3500000 | E6: Case: MXN 35,00,000
B7: Useful life (years) | C7: 10 | E7: Case: 10-yr straight-line
B8: Old equipment — book value / tax basis (MXN) | C8: 250000 | E8: Case
B9: Old equipment — market value (MXN) | C9: 175000 | E9: Case: cash-in on disposal
B10: Old equipment — remaining dep life (years) | C10: 3 | E10: Case: 3 yrs SL left
B11: Terminal / salvage value (MXN) | C11: 0 | E11: Case: salvage = disposal cost → net zero
B13: Rates, Inflation & Tax
B14: Euro hurdle rate (parent) | C14: 0.08 | E14: Case: 8% EUR — the ONLY discount rate to use
B15: Mexico inflation | C15: 0.07 | E15: Case: 7%
B16: France inflation | C16: 0.03 | E16: Case: 3%
B17: Spot exchange rate (MXN per EUR) | C17: 15.99 | E17: Case: MXN 15.99 / EUR on 23-Jun-2020
B18: Mexican corporate tax rate (BASE CASE) | C18: 0.33333333 | E18: Case: cash flows sit in Mexico → use 33.33%
B20: Derived (formulas)
B21: Peso hurdle via Fisher = (1+r€)(1+π_mx)/(1+π_fr) − 1 | C21: =(1+Assumptions!$C$14)*(1+Assumptions!$C$15)/(1+Assumptions!$C$16)-1 -> 0.12194175 | E21: Route A discount rate
B22: Annual peso depreciation vs PPP = (1+π_mx)/(1+π_fr) − 1 | C22: =(1+Assumptions!$C$15)/(1+Assumptions!$C$16)-1 -> 0.038834951 | E22: Peso weakens ~3.88%/yr (Route B path)
B23: New-equipment annual depreciation = Cost / life | C23: =Assumptions!$C$6/Assumptions!$C$7 -> 350000
B24: Old-equipment annual depreciation = Basis / rem. life | C24: =Assumptions!$C$8/Assumptions!$C$10 -> 83333.333
B26: Blue = input, Black = formula, Green = cross-sheet. TRAPS: (1) discount ONLY at 8% EUR / 12.19% peso — never the borrowing rates 4.99/8.10/9.21/4.75% (financing ≠ investment). (2) Old machine cash-in = MARKET 175,000, not book 250,000; book enters only via tax shield on the loss. (3) Incremental dep is 266,667 in yrs 1-3 (forgone old dep), 350,000 after. (4) Use Mexican 33.33% for project cash; French 35% is only for the repatriation discussion. Flip tax to 35% to reconcile with the case Excel exhibit.

Sheet Decision
B2: Decision & Parity Reconciliation
B4: Both routes must give the same answer
B5: Route A — NPV in MXN | C5: =RouteA_Peso!$C$11 -> 1555063.7 | E5: Peso cash flows @ 12.19%
B6: Route A — NPV in EUR (÷ spot) | C6: =RouteA_Peso!$C$12 -> 97252.264 | E6: Same project, stated in euros
B7: Route B — NPV in EUR (PPP path) | C7: =RouteB_Euro!$C$13 -> 97252.264 | E7: Euro cash flows @ 8%
B8: Difference (A − B), EUR — should be ≈ 0 | C8: =RouteA_Peso!$C$12-RouteB_Euro!$C$13 -> 0
B10: Decision
B11: NPV > 0 → ACCEPT the investment | C11: =IF(RouteB_Euro!$C$13>0,"ACCEPT","REJECT") -> ACCEPT
B13: Check figures (base case, t = 33.33%)
B14: Expected NPV (MXN) | C14: MXN 15,55,064
B15: Expected NPV (EUR) | C15: EUR 97,252
B16: Peso hurdle (Fisher) | C16: 12.19%
B17: Annual peso depreciation | C17: ~3.88%
B19: Discussion (earn the marks)
B20: Real peso depreciation | C20: Analysts expect the peso to weaken FASTER than PPP. Re-run Route B with a steeper devaluation → euro value of peso savings shrinks → lower NPV. Sensitivity, not base case.
B21: Country-risk premium | C21: Should the 8% hurdle carry a Mexico risk premium? If yes, discount rate rises and NPV falls. Judgment call.
B22: Financing ≠ investment | C22: Peso borrowing (8.10–9.21%) may HEDGE currency exposure but does NOT change project NPV. Keep financing separate.
B23: Tax rate | C23: Base uses Mexican 33.33% (cash lives in Mexico). The case Excel exhibit used 35% → NPV EUR 92,495. French 35% only matters for repatriation.

Sheet CashFlow_MXN
B2: After-Tax Cash Flows in Pesos (the project engine)
B4: Year | C4: 0 | D4: 1 | E4: 2 | F4: 3 | G4: 4 | H4: 5 | I4: 6 | J4: 7 | K4: 8 | L4: 9 | M4: 10
B5: Step 1 — Net Initial Investment (Year 0)
B6: Cost of new equipment | C6: =-Assumptions!$C$6 -> -3500000
B7: + Sale of old equipment (MARKET value) | C7: =Assumptions!$C$9 -> 175000
B8: + Tax shield on loss = (Basis − Market) × t | C8: =(Assumptions!$C$8-Assumptions!$C$9)*Assumptions!$C$18 -> 25000
B9: Net Initial Investment | C9: =C6+C7+C8 -> -3300000
B11: Step 2 — Incremental Depreciation (non-cash; drives tax shield)
B12: New-equipment depreciation | C12: =Assumptions!$C$23 -> 350000 | D12: =Assumptions!$C$23 -> 350000 | E12: =Assumptions!$C$23 -> 350000 | F12: =Assumptions!$C$23 -> 350000 | G12: =Assumptions!$C$23 -> 350000 | H12: =Assumptions!$C$23 -> 350000 | I12: =Assumptions!$C$23 -> 350000 | J12: =Assumptions!$C$23 -> 350000 | ... L12: =Assumptions!$C$23 -> 350000
B13: − Forgone old-equipment depreciation (yrs 1-3) | C13: =-Assumptions!$C$24 -> -83333.333 | D13: =-Assumptions!$C$24 -> -83333.333 | E13: =-Assumptions!$C$24 -> -83333.333 | F13: 0 | G13: 0 | H13: 0 | I13: 0 | J13: 0 | K13: 0 | L13: 0
B14: Incremental Depreciation (ΔD) | C14: =C12+C13 -> 266666.67 | D14: =D12+D13 -> 266666.67 | E14: =E12+E13 -> 266666.67 | F14: =F12+F13 -> 350000 | G14: =G12+G13 -> 350000 | H14: =H12+H13 -> 350000 | I14: =I12+I13 -> 350000 | J14: =J12+J13 -> 350000 | ... L14: =L12+L13 -> 350000
B16: Step 3 — Annual After-Tax Cash Flow = Savings×(1−t) + ΔD×t
B17: Pre-tax savings (from Savings tab) | C17: =Savings!$C$7 -> 727429 | D17: =Savings!$D$7 -> 844009 | E17: =Savings!$E$7 -> 980371 | F17: =Savings!$F$7 -> 1139956 | G17: =Savings!$G$7 -> 1219753 | H17: =Savings!$H$7 -> 1305136 | I17: =Savings!$I$7 -> 1396496 | J17: =Savings!$J$7 -> 1494251 | K17: =Savings!$K$7 -> 1598848 | L17: =Savings!$L$7 -> 1710767
B18: Savings × (1 − t) [after-tax savings] | C18: =C17*(1-Assumptions!$C$18) -> 484952.67 | D18: =D17*(1-Assumptions!$C$18) -> 562672.67 | E18: =E17*(1-Assumptions!$C$18) -> 653580.67 | F18: =F17*(1-Assumptions!$C$18) -> 759970.67 | G18: =G17*(1-Assumptions!$C$18) -> 813168.67 | H18: =H17*(1-Assumptions!$C$18) -> 870090.67 | I18: =I17*(1-Assumptions!$C$18) -> 930997.33 | J18: =J17*(1-Assumptions!$C$18) -> 996167.33 | ... L18: =L17*(1-Assumptions!$C$18) -> 1140511.3
B19: ΔD × t [depreciation tax shield] | C19: =C14*Assumptions!$C$18 -> 88888.889 | D19: =D14*Assumptions!$C$18 -> 88888.889 | E19: =E14*Assumptions!$C$18 -> 88888.889 | F19: =F14*Assumptions!$C$18 -> 116666.67 | G19: =G14*Assumptions!$C$18 -> 116666.67 | H19: =H14*Assumptions!$C$18 -> 116666.67 | I19: =I14*Assumptions!$C$18 -> 116666.67 | J19: =J14*Assumptions!$C$18 -> 116666.67 | ... L19: =L14*Assumptions!$C$18 -> 116666.67
B20: After-Tax Cash Flow (ATCF), MXN | C20: =C18+C19 -> 573841.56 | D20: =D18+D19 -> 651561.56 | E20: =E18+E19 -> 742469.56 | F20: =F18+F19 -> 876637.33 | G20: =G18+G19 -> 929835.33 | H20: =H18+H19 -> 986757.33 | I20: =I18+I19 -> 1047664 | J20: =J18+J19 -> 1112834 | ... L20: =L18+L19 -> 1257178
B21: Step 4 — Terminal value = 0 (salvage = disposal cost). No working capital mentioned → none.

Sheet RouteA_Peso
B2: ROUTE A — Discount Peso Cash Flows at the Peso Hurdle (12.19%)
B3: Stay in pesos the whole way. Convert the 8% euro hurdle into its peso twin via Fisher, discount, then divide the NPV by spot to state in euros.
B5: Year | C5: 0 | D5: 1 | E5: 2 | F5: 3 | G5: 4 | H5: 5 | I5: 6 | J5: 7 | K5: 8 | L5: 9 | M5: 10
B6: ATCF (MXN, from engine) | C6: =CashFlow_MXN!$C$9 -> -3300000 | D6: =CashFlow_MXN!$C$20 -> 573841.56 | E6: =CashFlow_MXN!$D$20 -> 651561.56 | F6: =CashFlow_MXN!$E$20 -> 742469.56 | G6: =CashFlow_MXN!$F$20 -> 876637.33 | H6: =CashFlow_MXN!$G$20 -> 929835.33 | I6: =CashFlow_MXN!$H$20 -> 986757.33 | J6: =CashFlow_MXN!$I$20 -> 1047664 | K6: =CashFlow_MXN!$J$20 -> 1112834 | L6: =CashFlow_MXN!$K$20 -> 1182565.3 | M6: =CashFlow_MXN!$L$20 -> 1257178
B7: Period | C7: 0 | D7: 1 | E7: 2 | F7: 3 | G7: 4 | H7: 5 | I7: 6 | J7: 7 | K7: 8 | L7: 9 | M7: 10
B8: Discount factor @ peso hurdle | C8: 1 | D8: =1/(1+Assumptions!$C$21)^D7 -> 0.89131187 | E8: =1/(1+Assumptions!$C$21)^E7 -> 0.79443685 | F8: =1/(1+Assumptions!$C$21)^F7 -> 0.708091 | G8: =1/(1+Assumptions!$C$21)^G7 -> 0.63112992 | H8: =1/(1+Assumptions!$C$21)^H7 -> 0.56253359 | I8: =1/(1+Assumptions!$C$21)^I7 -> 0.50139286 | J8: =1/(1+Assumptions!$C$21)^J7 -> 0.44689741 | K8: =1/(1+Assumptions!$C$21)^K7 -> 0.39832497 | ... M8: =1/(1+Assumptions!$C$21)^M7 -> 0.31644404
B9: PV of each cash flow (MXN) | C9: =C6*C8 -> -3300000 | D9: =D6*D8 -> 511471.79 | E9: =E6*E8 -> 517624.51 | F9: =F6*F8 -> 525736.01 | G9: =G6*G8 -> 553272.05 | H9: =H6*H8 -> 523063.61 | I9: =I6*I8 -> 494753.09 | J9: =J6*J8 -> 468198.33 | ... M9: =M6*M8 -> 397826.48
B11: NPV (MXN) | C11: =SUM(C9:M9) -> 1555063.7
B12: NPV (EUR) = NPV(MXN) / spot | C12: =C11/Assumptions!$C$17 -> 97252.264

Sheet RouteB_Euro
B2: ROUTE B — Convert Cash Flows to Euros, Discount at 8%
B3: Forecast the spot path with relative PPP: S(t) = spot × ((1+π_mx)/(1+π_fr))^t. Convert each year, discount euros at the 8% hurdle.
B5: Year | C5: 0 | D5: 1 | E5: 2 | F5: 3 | G5: 4 | H5: 5 | I5: 6 | J5: 7 | K5: 8 | L5: 9 | M5: 10
B6: ATCF (MXN, from engine) | C6: =CashFlow_MXN!$C$9 -> -3300000 | D6: =CashFlow_MXN!$C$20 -> 573841.56 | E6: =CashFlow_MXN!$D$20 -> 651561.56 | F6: =CashFlow_MXN!$E$20 -> 742469.56 | G6: =CashFlow_MXN!$F$20 -> 876637.33 | H6: =CashFlow_MXN!$G$20 -> 929835.33 | I6: =CashFlow_MXN!$H$20 -> 986757.33 | J6: =CashFlow_MXN!$I$20 -> 1047664 | K6: =CashFlow_MXN!$J$20 -> 1112834 | L6: =CashFlow_MXN!$K$20 -> 1182565.3 | M6: =CashFlow_MXN!$L$20 -> 1257178
B7: Period | C7: 0 | D7: 1 | E7: 2 | F7: 3 | G7: 4 | H7: 5 | I7: 6 | J7: 7 | K7: 8 | L7: 9 | M7: 10
B8: Forecast spot S(t) = spot×((1+π_mx)/(1+π_fr))^t | C8: =Assumptions!$C$17 -> 15.99 | D8: =Assumptions!$C$17*((1+Assumptions!$C$15)/(1+Assumptions!$C$16))^D7 -> 16.610971 | E8: =Assumptions!$C$17*((1+Assumptions!$C$15)/(1+Assumptions!$C$16))^E7 -> 17.256057 | F8: =Assumptions!$C$17*((1+Assumptions!$C$15)/(1+Assumptions!$C$16))^F7 -> 17.926195 | G8: =Assumptions!$C$17*((1+Assumptions!$C$15)/(1+Assumptions!$C$16))^G7 -> 18.622358 | H8: =Assumptions!$C$17*((1+Assumptions!$C$15)/(1+Assumptions!$C$16))^H7 -> 19.345557 | I8: =Assumptions!$C$17*((1+Assumptions!$C$15)/(1+Assumptions!$C$16))^I7 -> 20.09684 | J8: =Assumptions!$C$17*((1+Assumptions!$C$15)/(1+Assumptions!$C$16))^J7 -> 20.8773 | K8: =Assumptions!$C$17*((1+Assumptions!$C$15)/(1+Assumptions!$C$16))^K7 -> 21.688069 | ... M8: =Assumptions!$C$17*((1+Assumptions!$C$15)/(1+Assumptions!$C$16))^M7 -> 23.405288
B9: Cash flow in EUR = MXN / S(t) | C9: =C6/C8 -> -206378.99 | D9: =D6/D8 -> 34545.937 | E9: =E6/E8 -> 37758.426 | F9: =F6/F8 -> 41418.134 | G9: =G6/G8 -> 47074.453 | H9: =H6/H8 -> 48064.543 | I9: =I6/I8 -> 49100.123 | J9: =J6/J8 -> 50181.968 | ... M9: =M6/M8 -> 53713.417
B10: Discount factor @ 8% euro hurdle | C10: 1 | D10: =1/(1+Assumptions!$C$14)^D7 -> 0.92592593 | E10: =1/(1+Assumptions!$C$14)^E7 -> 0.85733882 | F10: =1/(1+Assumptions!$C$14)^F7 -> 0.79383224 | G10: =1/(1+Assumptions!$C$14)^G7 -> 0.73502985 | H10: =1/(1+Assumptions!$C$14)^H7 -> 0.6805832 | I10: =1/(1+Assumptions!$C$14)^I7 -> 0.63016963 | J10: =1/(1+Assumptions!$C$14)^J7 -> 0.5834904 | K10: =1/(1+Assumptions!$C$14)^K7 -> 0.54026888 | ... M10: =1/(1+Assumptions!$C$14)^M7 -> 0.46319349
B11: PV of each cash flow (EUR) | C11: =C9*C10 -> -206378.99 | D11: =D9*D10 -> 31986.979 | E11: =E9*E10 -> 32371.764 | F11: =F9*F10 -> 32879.05 | G11: =G9*G10 -> 34601.129 | H11: =H9*H10 -> 32711.92 | I11: =I9*I10 -> 30941.406 | J11: =J9*J10 -> 29280.696 | ... M11: =M9*M10 -> 24879.705
B13: NPV (EUR) | C13: =SUM(C11:M11) -> 97252.264

Sheet Savings
B2: Exhibit 1 — Pre-tax Cost Savings (Manual − Automatic), MXN
B4: Year | C4: 1 | D4: 2 | E4: 3 | F4: 4 | G4: 5 | H4: 6 | I4: 7 | J4: 8 | K4: 9 | L4: 10
B5: Total operating cost — Manual | C5: 3360000 | D5: 3774960 | E5: 4250785 | F5: 4797366 | G5: 5133182 | H5: 5492505 | I5: 5876980 | J5: 6288369 | K5: 6728555 | L5: 7199553
B6: Total operating cost — Automatic | C6: 2632571 | D6: 2930951 | E6: 3270414 | F6: 3657410 | G6: 3913429 | H6: 4187369 | I6: 4480484 | J6: 4794118 | K6: 5129707 | L6: 5488786
B7: Pre-tax Savings (Manual − Automatic) | C7: =C5-C6 -> 727429 | D7: =D5-D6 -> 844009 | E7: =E5-E6 -> 980371 | F7: =F5-F6 -> 1139956 | G7: =G5-G6 -> 1219753 | H7: =H5-H6 -> 1305136 | I7: =I5-I6 -> 1396496 | J7: =J5-J6 -> 1494251 | ... L7: =L5-L6 -> 1710767
B9: Source: Case Exhibit 1 (Panel A Manual, Panel B Automatic). Values are total peso operating costs; savings feed the cash-flow engine.
