Workbook

Sheet Assumptions
B2: AVIVA / Airlead — Key Assumptions & Inputs
B4: Cost of Capital (CAPM / WACC)
B5: Risk-free rate (5.50% debt yield − 1.25% spread) | C5: 0.0425 | J5: Case p.2: 5.50% = 125bp over 10yr UST
B6: Equity market risk premium (ERP) | C6: 0.05 | J6: Case p.2: Ripsy uses 5% ERP
B7: Comparable average levered beta | C7: 1 | J7: Exhibit 2: average beta = 1.00
B8: Comparable average D/E | C8: 0.401 | J8: Exhibit 2: average D/E = 40.1%
B9: Tax rate | C9: 0.4 | J9: Exhibit 1: tax 40%
B10: Unlevered beta = levβ/(1+(1-t)*D/E) | C10: =C7/(1+(1-C9)*C8) -> 0.80606158
B11: Target Debt/Value | C11: 0.5 | J11: Case p.2: D/V ≤ 50% (5.0x EBITDA)
B12: Target Debt/Equity = (D/V)/(1-D/V) | C12: =C11/(1-C11) -> 1
B13: Relevered beta = unlevβ*(1+(1-t)*D/E) | C13: =C10*(1+(1-C9)*C12) -> 1.2896985
B14: Cost of equity Ke = Rf + β*ERP | C14: =C5+C13*C6 -> 0.10698493
B15: Pre-tax cost of debt Kd | C15: 0.055 | J15: Case p.2: AVIVA rate ~5.50%, BBB+
B16: After-tax Kd = Kd*(1-t) | C16: =C15*(1-C9) -> 0.033
B17: WACC = (E/V)*Ke + (D/V)*Kd*(1-t) | C17: =(1-C11)*C14+C11*C16 -> 0.069992463
B20: Terminal Value & Deal Inputs
B21: Perpetuity growth rate (g) | C21: 0.05 | J21: Per user: = equipment revenue growth
B22: Terminal EV/EBITDA multiple (market method) | C22: 5 | J22: Case p.2: D/V target 5.0x EBITDA
B23: Comparable median EV/EBITDA (cross-check) | C23: =Comps!H13 -> 10.338521 | J23: Link: Comps tab
B24: Acquisition debt / EBITDA (entry leverage) | C24: 5 | J24: Case p.2
B25: Airlead operating EBITDA 2016 ($MM) | C25: 1033.3 | J25: Case p.2
B26: Opening net debt 2017 ($MM) | C26: 3758 | J26: Exhibit 3
B28: Private-Company Discounts / Premiums
B29: Illiquidity (DLOM) discount | C29: 0.35 | J29: Case p.2: academic ~35%
B30: Control premium | C30: 0.3 | J30: Case p.2: academic ~30%
B31: BBB+ default probability | C31: 0.023 | J31: Exhibit 4: BBB = 2.30%
B32: Bankruptcy cost (% of unlevered value) | C32: 0.25 | J32: Case p.2: direct+indirect up to 25%
B34: Blue = input | Black = formula | Green = cross-sheet link. Terminal value = average of 5.0% growth perpetuity AND 5.0x EBITDA market multiple. Lens = acquirer view (standalone DCF + PV of synergies), then expected bankruptcy cost, control premium and illiquidity discount.

Sheet ReadMe_Findings
B2: AVIVA / Airlead — How to Read This Model & Key Judgment Calls
B4: TAB GUIDE
B5: • Assumptions — all blue inputs (WACC build, terminal value, discounts). Change these to flex the model.
B6: • Valuation — the answer: standalone EV + synergies → bankruptcy adj → net debt → control premium → DLOM → equity value.
B7: • DCF_Base — Airlead standalone unlevered DCF (Exhibit 1 operating model). Terminal value via BOTH growth perpetuity and 5.0x EBITDA.
B8: • Synergies — backhaul savings + cross-sell revenue, after-tax, with a conservative synergy terminal growth input.
B9: • Comps — Exhibit 2, with computed EV/EBITDA (avg ~9.2x, median ~10.3x) as the multiple cross-check.
B10: • LBO_Debt — entry leverage (5.0x EBITDA) and the Exhibit 3 debt schedule for credit/feasibility context.
B12: HEADLINE NUMBERS (at current inputs)
B13: • WACC ≈ 7.0% (Ke 10.7% via relevered β 1.29; after-tax Kd 3.3%; 50/50 capital structure)
B14: • Standalone Enterprise Value ≈ $10.3B
B15: • PV of Synergies ≈ $7.9B
... B30: The standalone DCF (~$10.3B EV) is the solid anchor. The headline equity value swings most on (a) the terminal-value method you trust and (b) how you net the cross-sell revenue. Present a RANGE — roughly $8–13B equity — rather than a single point, and walk the audience through the four calls above. That is the analysis this case is actually testing.

Sheet Valuation
B2: Valuation Summary — Acquirer View ($MM)
B4: A. Enterprise Value Build
B5: Standalone Enterprise Value (DCF base) | C5: =DCF_Base!$G$38 -> 10277.388
B6: (+) PV of Synergies (backhaul + cross-sell) | C6: =Synergies!$G$20 -> 7864.586
B7: Combined Enterprise Value (with synergies) | C7: =C5+C6 -> 18141.974
B9: B. Distress / Bankruptcy Adjustment
B10: Expected bankruptcy cost = PD × Cost% × EV | C10: =-Assumptions!$C$29*Assumptions!$C$29*C7 -> -2222.3918 | E10: PD: Exhibit 4 (BBB 2.30%); cost up to 25%
B11: Enterprise Value, net of expected distress | C11: =C7+C10 -> 15919.582
B13: C. Bridge to Equity Value
B14: (–) Net Debt (opening 2017) | C14: =-Assumptions!$C$26 -> -3758 | E14: Exhibit 3
B15: Equity Value (pre private-co adjustments) | C15: =C11+C14 -> 12161.582
B17: D. Private-Company Adjustments
B18: (+) Control premium | C18: =C15*Assumptions!$C$29 -> 4256.5537 | E18: Academic ~30%
B19: Equity Value incl. control premium | C19: =C15+C18 -> 16418.136
B20: (–) Illiquidity / DLOM discount | C20: =-C19*Assumptions!$C$29 -> -5746.3475 | E20: Academic ~35%
B21: FINAL EQUITY VALUE (private, acquirer view) | C21: =C19+C20 -> 10671.788
B23: E. Implied Metrics (sanity check)
B24: Implied EV / 2016 EBITDA | C24: =C7/Assumptions!$C$25 -> 17.557315
B25: Implied EV / 2017 EBITDA | C25: =C7/(DCF_Base!C14+DCF_Base!C13) -> 16.32794
B26: Synergies as % of standalone EV | C26: =C6/C5 -> 0.76523199
B27: Total discount haircut vs pre-adj equity | C27: =C21/C15-1 -> -0.1225

Sheet DCF_Base
B2: Airlead — Standalone DCF (Base Case, $MM)
B4: Fiscal Year | C4: 2017 | D4: 2018 | E4: 2019 | F4: 2020 | G4: 2021
B5: Revenue
B6: Service Revenue | C6: 4194.3 | D6: 4781.5 | E6: 5379.2 | F6: 5917.2 | G6: 6331.4
B7: Equipment Revenue | C7: 314.8 | D7: 358.8 | E7: 403.7 | F7: 444.1 | G7: 475.2
B8: Total Revenue | C8: =C6+C7 -> 4509.1 | D8: =D6+D7 -> 5140.3 | E8: =E6+E7 -> 5782.9 | F8: =F6+F7 -> 6361.3 | G8: =G6+G7 -> 6806.6
B9: Operating Expenses
B10: System Operating Expenses | C10: 838.9 | D10: 956.3 | E10: 1075.8 | F10: 1183.4 | G10: 1266.3
B11: Equipment COGS | C11: 755.5 | D11: 861.2 | E11: 968.9 | F11: 1065.8 | G11: 1140.4
B12: Selling, General & Administrative | C12: 1803.6 | D12: 2056.2 | E12: 2313.2 | F12: 2544.5 | G12: 2722.6
B13: Depreciation & Amortization | C13: 705.2 | D13: 804 | E13: 867.4 | F13: 922.4 | G13: 952.9
B14: EBIT | C14: =C8-C10-C11-C12-C13 -> 405.9 | D14: =D8-D10-D11-D12-D13 -> 462.6 | E14: =E8-E10-E11-E12-E13 -> 557.6 | F14: =F8-F10-F11-F12-F13 -> 645.2 | G14: =G8-G10-G11-G12-G13 -> 724.4
B15: Less: Tax on EBIT | C15: =-C14*Assumptions!$C$9 -> -162.36 | D15: =-D14*Assumptions!$C$9 -> -185.04 | E15: =-E14*Assumptions!$C$9 -> -223.04 | F15: =-F14*Assumptions!$C$9 -> -258.08 | G15: =-G14*Assumptions!$C$9 -> -289.76
B16: NOPAT (EBIAT) | C16: =C14+C15 -> 243.54 | D16: =D14+D15 -> 277.56 | E16: =E14+E15 -> 334.56 | F16: =F14+F15 -> 387.12 | G16: =G14+G15 -> 434.64
B17: Free Cash Flow Build
B18: Add: D&A | C18: =C13 -> 705.2 | D18: =D13 -> 804 | E18: =E13 -> 867.4 | F18: =F13 -> 922.4 | G18: =G13 -> 952.9
B19: Less: Capital Expenditures | C19: -631.3 | D19: -719.7 | E19: -867.4 | F19: -970.1 | G19: -1055
B20: Less: Δ NWC (3% of Δ revenue) | C20: =-0.03*(C8-3955.3) -> -16.614 | D20: =-0.03*(D8-C8) -> -18.936 | E20: =-0.03*(E8-D8) -> -19.278 | F20: =-0.03*(F8-E8) -> -17.352 | G20: =-0.03*(G8-F8) -> -13.359
B21: Unlevered Free Cash Flow | C21: =C16+C18+C19+C20 -> 300.826 | D21: =D16+D18+D19+D20 -> 342.924 | E21: =E16+E18+E19+E20 -> 315.282 | F21: =F16+F18+F19+F20 -> 322.068 | G21: =G16+G18+G19+G20 -> 319.181
B23: Discounting (year-end convention)
B24: Discount period (yrs) | C24: 1 | D24: 2 | E24: 3 | F24: 4 | G24: 5
B25: Discount factor @ WACC | C25: =1/(1+Assumptions!$C$17)^C24 -> 0.93458602 | D25: =1/(1+Assumptions!$C$17)^D24 -> 0.87345103 | E25: =1/(1+Assumptions!$C$17)^E24 -> 0.81631513 | F25: =1/(1+Assumptions!$C$17)^F24 -> 0.76291671 | G25: =1/(1+Assumptions!$C$17)^G24 -> 0.71301129
B26: PV of Unlevered FCF | C26: =C21*C25 -> 281.14777 | D26: =D21*D25 -> 299.52732 | E26: =E21*E25 -> 257.36947 | F26: =F21*F25 -> 245.71106 | G26: =G21*G25 -> 227.57966
B28: Terminal Value (end of 2021)
B29: TV — Gordon growth = FCF*(1+g)/(WACC-g) | G29: =G21*(1+Assumptions!$C$21)/(Assumptions!$C$17-Assumptions!$C$21) -> 16763.319
B30: EBITDA 2021 (= EBIT + D&A) | G30: =G14+G13 -> 1677.3
B31: TV — Market = EBITDA × EV/EBITDA | G31: =G30*Assumptions!$C$22 -> 8386.5
B32: Selected TV (avg of two methods) | G32: =AVERAGE(G29,G31) -> 12574.91
B33: PV of Terminal Value | G33: =G32*G25 -> 8966.0526
B35: Standalone Enterprise Value
B36: Sum PV of explicit FCF (2017–21) | G36: =SUM(C26:G26) -> 1311.3353
B37: PV of Terminal Value | G37: =G33 -> 8966.0526
B38: Enterprise Value — Standalone (Base) | G38: =G36+G37 -> 10277.388

Sheet Synergies
B2: Synergies — Backhaul Savings + Cross-Sell ($MM)
B4: Fiscal Year | C4: 2017 | D4: 2018 | E4: 2019 | F4: 2020 | G4: 2021
B5: 1. Backhaul Cost Savings (pre-tax)
B6: Backhaul Savings (pre-tax) | C6: 0 | D6: 13.4 | E6: 25.8 | F6: 52.5 | G6: 76
B7: 2. Cross-Sell / Bundling Incremental Revenue
B8: Annual Incremental Revenue (pre-tax) | C8: 156 | D8: 269 | E8: 387 | F8: 570 | G8: 704
B9: Combined After-Tax Synergy Cash Flow
B10: Total pre-tax synergies | C10: =C6+C8 -> 156 | D10: =D6+D8 -> 282.4 | E10: =E6+E8 -> 412.8 | F10: =F6+F8 -> 622.5 | G10: =G6+G8 -> 780
B11: After-tax synergy FCF = pre-tax*(1-t) | C11: =C10*(1-Assumptions!$C$9) -> 93.6 | D11: =D10*(1-Assumptions!$C$9) -> 169.44 | E11: =E10*(1-Assumptions!$C$9) -> 247.68 | F11: =F10*(1-Assumptions!$C$9) -> 373.5 | G11: =G10*(1-Assumptions!$C$9) -> 468
B13: PV of Synergies
B14: Discount period | C14: 1 | D14: 2 | E14: 3 | F14: 4 | G14: 5
B15: Discount factor @ WACC | C15: =1/(1+Assumptions!$C$17)^C14 -> 0.93458602 | D15: =1/(1+Assumptions!$C$17)^D14 -> 0.87345103 | E15: =1/(1+Assumptions!$C$17)^E14 -> 0.81631513 | F15: =1/(1+Assumptions!$C$17)^F14 -> 0.76291671 | G15: =1/(1+Assumptions!$C$17)^G14 -> 0.71301129
B16: PV of after-tax synergies | C16: =C11*C15 -> 87.477252 | D16: =D11*D15 -> 147.99754 | E16: =E11*E15 -> 202.18493 | F16: =F11*F15 -> 284.94939 | G16: =G11*G15 -> 333.68928
B17: TV of synergies = AT*(1+g_syn)/(WACC-g_syn) | G17: =G11*(1+Synergies!$C$22)/(Assumptions!$C$17-Synergies!$C$22) -> 9548.6393
B18: PV of synergy terminal value | G18: =G17*G15 -> 6808.2876
B20: Total PV of Synergies | G20: =SUM(C16:G16)+G18 -> 7864.586
B22: Synergy terminal growth (conservative input) | C22: 0.02 | D22: ← lower than 5% op. growth: synergies still ramping in 2021

Sheet Comps
B2: Exhibit 2 — Comparable Company Data ($MM)
B4: Company | C4: Equity MV | D4: Net Debt | E4: Debt/Value | F4: D/E | G4: Beta | H4: Revenue | I4: EBIT | J4: EBITDA | K4: Net Income | L4: EV/EBITDA
B5: Axel Mobile | C5: 118497 | D5: 69130 | E5: 0.368 | F5: 0.583 | G5: 0.86 | H5: 43882 | I5: 11795 | J5: 16949 | K5: =(C5+D5)/J5 -> 11.070093
B6: Wills Wireless | C6: 189470 | D6: 79351 | E6: 0.295 | F6: 0.419 | G6: 0.89 | H6: 42684 | I6: 7020 | J6: 14099 | K6: =(C6+D6)/J6 -> 19.066671
B7: Agile Mobile | C7: 21079 | D7: 5080 | E7: 0.194 | F7: 0.241 | G7: 1.17 | H7: 34698 | I7: 1631 | J7: 9914 | K7: =(C7+D7)/J7 -> 2.6385919
B8: Big Mobile | C8: 26285 | D8: 8335 | E8: 0.241 | F8: 0.317 | G8: 0.97 | H8: 38896 | I8: 6702 | J8: 12614 | K8: =(C8+D8)/J8 -> 2.7445695
B9: Rocky Comm | C9: 7360 | D9: 3268 | E9: 0.307 | F9: 0.444 | G9: 1.13 | H9: 4064 | I9: 510 | J9: 1028 | K9: =(C9+D9)/J9 -> 10.338521
B12: Average | F12: =AVERAGE(F5:F9) -> 0.4008 | G12: =AVERAGE(G5:G9) -> 1.004 | K12: =AVERAGE(K5:K9) -> 9.1716894
B13: Median | H13: =MEDIAN(K5:K9) -> 10.338521 | L13: median EV/EBITDA (cross-check)

Sheet LBO_Debt
B2: Acquisition Debt & Leverage (LBO context, $MM)
B4: Fiscal Year | C4: 2017 | D4: 2018 | E4: 2019 | F4: 2020 | G4: 2021
B5: Entry acquisition debt = 5.0x EBITDA 2016 | C5: =Assumptions!$C$24*Assumptions!$C$25 -> 5166.5
B7: Existing Debt Schedule (Exhibit 3, reference)
B8: Opening Debt | C8: 3758 | D8: 3468 | E8: 3161 | F8: 2838 | G8: 2496
B9: Interest Paid | C9: 199.4 | D9: 183.1 | E9: 165.8 | F9: 147.5 | G9: 128.3
B10: Principal Repayment | C10: 290 | D10: 307 | E10: 323 | F10: 342 | G10: 2496
B11: Closing Debt | C11: =C8-C10 -> 3468 | D11: =D8-D10 -> 3161 | E11: =E8-E10 -> 2838 | F11: =F8-F10 -> 2496 | G11: =G8-G10 -> 0
B12: Implied interest rate | C12: =C9/C8 -> 0.053060138 | D12: =D9/D8 -> 0.052797001 | E12: =E9/E8 -> 0.052451756 | F12: =F9/F8 -> 0.051973221 | G12: =G9/G8 -> 0.051402244
B14: Note: Entry leverage 5.0x EBITDA is paid toward industry norms (D/V ≤ 50%, BBB+). Acquisition debt is a single 10-yr amortizing tranche with a bullet at end of year 5. Interest tax shield is captured through WACC, so operations are valued unlevered in the DCF; this schedule supports credit/feasibility rather than re-discounting cash flows.
