Workbook

Sheet Assumptions
B2: Three Ways to Value One Firm — WACC vs CCF vs APV
B3: A deliberately simple firm with a FIXED debt-repayment schedule. All three methods give the SAME enterprise value.
B5: Operating Inputs
B6: EBIT — Year 1 ($MM) | C6: 1000 | J6: Flat EBIT for simplicity (no growth)
B7: EBIT growth rate | C7: 0 | J7: Set to 0% so cash flow is constant & easy to trace
B8: Tax rate (t) | C8: 0.3 | J8: Clean round number
B9: D&A ($MM, = CapEx, so they cancel) | C9: 200 | J9: D&A = CapEx → no net reinvestment, keeps FCFF clean
B10: CapEx ($MM) | C10: 200 | J10: Equals D&A on purpose
B11: Change in NWC ($MM) | C11: 0 | J11: Zero for simplicity
B13: Discount Rates
B14: Unlevered cost of equity / asset return (Ka) | C14: 0.1 | J14: THE key rate. Property of the assets — does NOT change with leverage.
B15: Pre-tax cost of debt (Kd) | C15: 0.06 | J15: What lenders charge
B16: Risk-free rate (for reference) | C16: 0.04 | J16: Not used directly here; shown for context
B18: Capital Structure (FIXED debt schedule — the LBO case)
B19: Opening Debt — Year 1 ($MM) | C19: 3500 | J19: High initial leverage, like an LBO
B20: Annual principal repayment ($MM) | C20: 700 | J20: Fixed $ amount each year → debt deleverages → D/V keeps falling
B22: THE BIG IDEA: The tax shield (Interest × t) is worth money, so it must be counted EXACTLY ONCE. WACC hides it in the discount rate (after-tax Kd). CCF puts it in the cash flow and discounts at Ka. APV values it as a separate term discounted at Kd. Because debt here is a FIXED schedule, D/V falls every year — so a single WACC is technically wrong, and CCF/APV (which discount operations at the leverage-independent Ka) are the correct tools. Watch the WACC tab: the implied WACC drifts each year, but Ka never moves.

Sheet CashFlows
B2: Debt Schedule & Cash Flows (shared by all methods)
B4: Period | C4: Year 1 | D4: Year 2 | E4: Year 3 | F4: Year 4 | G4: Year 5
B5: Debt Schedule (fixed repayment)
B6: Opening Debt | C6: =Assumptions!$C$19 -> 3500 | D6: =C6-C8 -> 2800 | E6: =D6-D8 -> 2100 | F6: =E6-E8 -> 1400 | G6: =F6-F8 -> 700
B7: Interest = Opening Debt × Kd | C7: =C6*Assumptions!$C$15 -> 210 | D7: =D6*Assumptions!$C$15 -> 168 | E7: =E6*Assumptions!$C$15 -> 126 | F7: =F6*Assumptions!$C$15 -> 84 | G7: =G6*Assumptions!$C$15 -> 42
B8: Principal Repayment | C8: =MIN(Assumptions!$C$20,C6) -> 700 | D8: =MIN(Assumptions!$C$20,D6) -> 700 | E8: =MIN(Assumptions!$C$20,E6) -> 700 | F8: =MIN(Assumptions!$C$20,F6) -> 700 | G8: =MIN(Assumptions!$C$20,G6) -> 700
B9: Closing Debt | C9: =C6-C8 -> 2800 | D9: =D6-D8 -> 2100 | E9: =E6-E8 -> 1400 | F9: =F6-F8 -> 700 | G9: =G6-G8 -> 0
B10: Tax Shield = Interest × t | C10: =C7*Assumptions!$C$8 -> 63 | D10: =D7*Assumptions!$C$8 -> 50.4 | E10: =E7*Assumptions!$C$8 -> 37.8 | F10: =F7*Assumptions!$C$8 -> 25.2 | G10: =G7*Assumptions!$C$8 -> 12.6
B12: Operating Cash Flow Build
B13: EBIT | C13: =Assumptions!$C$6 -> 1000 | D13: =C13*(1+Assumptions!$C$7) -> 1000 | E13: =D13*(1+Assumptions!$C$7) -> 1000 | F13: =E13*(1+Assumptions!$C$7) -> 1000 | G13: =F13*(1+Assumptions!$C$7) -> 1000
B14: NOPAT = EBIT × (1 − t) | C14: =C13*(1-Assumptions!$C$8) -> 700 | D14: =D13*(1-Assumptions!$C$8) -> 700 | E14: =E13*(1-Assumptions!$C$8) -> 700 | F14: =F13*(1-Assumptions!$C$8) -> 700 | G14: =G13*(1-Assumptions!$C$8) -> 700
B15: + D&A | C15: =Assumptions!$C$9 -> 200 | D15: =Assumptions!$C$9 -> 200 | E15: =Assumptions!$C$9 -> 200 | F15: =Assumptions!$C$9 -> 200 | G15: =Assumptions!$C$9 -> 200
B16: − CapEx | C16: =-Assumptions!$C$10 -> -200 | D16: =-Assumptions!$C$10 -> -200 | E16: =-Assumptions!$C$10 -> -200 | F16: =-Assumptions!$C$10 -> -200 | G16: =-Assumptions!$C$10 -> -200
B17: − Change in NWC | C17: =-Assumptions!$C$11 -> 0 | D17: =-Assumptions!$C$11 -> 0 | E17: =-Assumptions!$C$11 -> 0 | F17: =-Assumptions!$C$11 -> 0 | G17: =-Assumptions!$C$11 -> 0
B18: FCFF (Unlevered Free Cash Flow) | C18: =C14+C15+C16+C17 -> 700 | D18: =D14+D15+D16+D17 -> 700 | E18: =E14+E15+E16+E17 -> 700 | F18: =F14+F15+F16+F17 -> 700 | G18: =G14+G15+G16+G17 -> 700
B19: CCF = FCFF + Tax Shield | C19: =C18+C10 -> 763 | D19: =D18+D10 -> 750.4 | E19: =E18+E10 -> 737.8 | F19: =F18+F10 -> 725.2 | G19: =G18+G10 -> 712.6
B21: This tab feeds all three valuation tabs. FCFF (navy) and CCF (green) differ by exactly the Tax Shield row above.

Sheet M1_WACC
B2: METHOD 1 — FCFF discounted at WACC
B3: Shield lives in the DISCOUNT RATE (after-tax Kd). Assumes a CONSTANT target D/V. We use a single target WACC here — but note the implied WACC actually drifts (shown below), which is exactly why this method is imperfect for deleveraging firms.
B5: Period | C5: Year 1 | D5: Year 2 | E5: Year 3 | F5: Year 4 | G5: Year 5
B6: WACC Inputs (target capital structure simplification)
B7: Target Debt / Value (D/V) — assumption | C7: 0.4
B8: Relevered Ke = Ka + (Ka−Kd)×(D/E) | C8: =Assumptions!$C$14+(Assumptions!$C$14-Assumptions!$C$15)*(M1_WACC!$C$7/(1-M1_WACC!$C$7)) -> 0.12666667
B9: WACC = (1−D/V)×Ke + (D/V)×Kd×(1−t) | C9: =(1-M1_WACC!$C$7)*C8+M1_WACC!$C$7*Assumptions!$C$15*(1-Assumptions!$C$8) -> 0.0928
B11: Discount FCFF at WACC
B12: FCFF (from CashFlows tab) | C12: =CashFlows!$C$18 -> 700 | D12: =CashFlows!$D$18 -> 700 | E12: =CashFlows!$E$18 -> 700 | F12: =CashFlows!$F$18 -> 700 | G12: =CashFlows!$G$18 -> 700
B13: Period | C13: 1 | D13: 2 | E13: 3 | F13: 4 | G13: 5
B14: Discount factor = 1/(1+WACC)^t | C14: =1/(1+M1_WACC!$C$9)^C13 -> 0.91508053 | D14: =1/(1+M1_WACC!$C$9)^D13 -> 0.83737237 | E14: =1/(1+M1_WACC!$C$9)^E13 -> 0.76626315 | F14: =1/(1+M1_WACC!$C$9)^F13 -> 0.70119249 | G14: =1/(1+M1_WACC!$C$9)^G13 -> 0.64164759
B15: PV of FCFF | C15: =C12*C14 -> 640.55637 | D15: =D12*D14 -> 586.16066 | E15: =E12*E14 -> 536.38421 | F15: =F12*F14 -> 490.83474 | G15: =G12*G14 -> 449.15331
B16: Terminal Value = FCFF₅ / Ka (debt-free terminal) | G16: =G12/Assumptions!$C$14 -> 7000
B17: PV of Terminal Value | G17: =G16*G14 -> 4491.5331
B19: ENTERPRISE VALUE (WACC method) | C19: =SUM(C15:G15)+G17 -> 7194.6224
B21: ⚠ Why a single WACC is imperfect here: implied annual D/V and WACC
B22: Opening Debt (from CashFlows) | C22: =CashFlows!$C$6 -> 3500 | D22: =CashFlows!$D$6 -> 2800 | E22: =CashFlows!$E$6 -> 2100 | F22: =CashFlows!$F$6 -> 1400 | G22: =CashFlows!$G$6 -> 700
B23: (Debt falls every year, so true D/V and true WACC drift — a constant WACC can't capture this. CCF & APV fix it.)

Sheet M2_CCF
B2: METHOD 2 — Capital Cash Flow (CCF) discounted at Ka
B3: Shield lives in the CASH FLOW (CCF = FCFF + shield). Discount EVERYTHING at Ka — the leverage-independent asset rate. Ka never changes, so deleveraging is no problem.
B5: Period | C5: Year 1 | D5: Year 2 | E5: Year 3 | F5: Year 4 | G5: Year 5
B6: CCF (from CashFlows tab) | C6: =CashFlows!$C$19 -> 763 | D6: =CashFlows!$D$19 -> 750.4 | E6: =CashFlows!$E$19 -> 737.8 | F6: =CashFlows!$F$19 -> 725.2 | G6: =CashFlows!$G$19 -> 712.6
B7: Period | C7: 1 | D7: 2 | E7: 3 | F7: 4 | G7: 5
B8: Discount factor = 1/(1+Ka)^t | C8: =1/(1+Assumptions!$C$14)^C7 -> 0.90909091 | D8: =1/(1+Assumptions!$C$14)^D7 -> 0.82644628 | E8: =1/(1+Assumptions!$C$14)^E7 -> 0.7513148 | F8: =1/(1+Assumptions!$C$14)^F7 -> 0.68301346 | G8: =1/(1+Assumptions!$C$14)^G7 -> 0.62092132
B9: PV of CCF | C9: =C6*C8 -> 693.63636 | D9: =D6*D8 -> 620.16529 | E9: =E6*E8 -> 554.32006 | F9: =F6*F8 -> 495.32136 | G9: =G6*G8 -> 442.46853
B10: Terminal Value = FCFF₅ / Ka (debt-free, no shield) | G10: =CashFlows!$G$18/Assumptions!$C$14 -> 7000
B11: PV of Terminal Value | G11: =G10*G8 -> 4346.4493
B13: ENTERPRISE VALUE (CCF method) | C13: =SUM(C9:G9)+G11 -> 7152.3609
B15: Note: TV uses CCF₅/Ka. In a true steady state, debt would stabilise; the no-growth perpetuity keeps the teaching example clean and comparable across all three methods.

Sheet M3_APV
B2: METHOD 3 — Adjusted Present Value (APV)
B3: Value the unlevered business (FCFF at Ka) + value the tax shield SEPARATELY (shield at Kd, because debt is a fixed schedule). Two pieces, added together.
B5: Period | C5: Year 1 | D5: Year 2 | E5: Year 3 | F5: Year 4 | G5: Year 5
B6: Piece 1 — Unlevered business value (FCFF at Ka)
B7: FCFF (from CashFlows tab) | C7: =CashFlows!$C$18 -> 700 | D7: =CashFlows!$D$18 -> 700 | E7: =CashFlows!$E$18 -> 700 | F7: =CashFlows!$F$18 -> 700 | G7: =CashFlows!$G$18 -> 700
B8: Period | C8: 1 | D8: 2 | E8: 3 | F8: 4 | G8: 5
B9: Discount factor = 1/(1+Ka)^t | C9: =1/(1+Assumptions!$C$14)^C8 -> 0.90909091 | D9: =1/(1+Assumptions!$C$14)^D8 -> 0.82644628 | E9: =1/(1+Assumptions!$C$14)^E8 -> 0.7513148 | F9: =1/(1+Assumptions!$C$14)^F8 -> 0.68301346 | G9: =1/(1+Assumptions!$C$14)^G8 -> 0.62092132
B10: PV of FCFF at Ka | C10: =C7*C9 -> 636.36364 | D10: =D7*D9 -> 578.5124 | E10: =E7*E9 -> 525.92036 | F10: =F7*F9 -> 478.10942 | G10: =G7*G9 -> 434.64493
B11: Terminal Value = FCFF₅ / Ka | G11: =G7/Assumptions!$C$14 -> 7000
B12: PV of Terminal Value | G12: =G11*G9 -> 4346.4493
B13: Unlevered Enterprise Value (Vu) | C13: =SUM(C10:G10)+G12 -> 7000
B15: Piece 2 — PV of the Tax Shield (at Kd, fixed-schedule logic)
B16: Tax Shield (from CashFlows tab) | C16: =CashFlows!$C$10 -> 63 | D16: =CashFlows!$D$10 -> 50.4 | E16: =CashFlows!$E$10 -> 37.8 | F16: =CashFlows!$F$10 -> 25.2 | G16: =CashFlows!$G$10 -> 12.6
B17: Discount factor = 1/(1+Kd)^t | C17: =1/(1+Assumptions!$C$15)^C8 -> 0.94339623 | D17: =1/(1+Assumptions!$C$15)^D8 -> 0.88999644 | E17: =1/(1+Assumptions!$C$15)^E8 -> 0.83961928 | F17: =1/(1+Assumptions!$C$15)^F8 -> 0.79209366 | G17: =1/(1+Assumptions!$C$15)^G8 -> 0.74725817
B18: PV of Tax Shield | C18: =C16*C17 -> 59.433962 | D18: =D16*D17 -> 44.855821 | E18: =E16*E17 -> 31.737609 | F18: =F16*F17 -> 19.96076 | G18: =G16*G17 -> 9.415453
B19: Terminal shield value = 0 (debt fully repaid by Year 5) | G19: 0
B20: PV of Terminal Shield | G20: 0
B21: PV of Tax Shield (total) | C21: =SUM(C18:G18)+G20 -> 165.40361
B23: ENTERPRISE VALUE (APV) = Vu + PV(shield) | C23: =C13+C21 -> 7165.4036
B25: APV makes the shield VISIBLE as its own number — you can literally see how much value the debt adds. In a real LBO you would also SUBTRACT PV of expected bankruptcy/distress costs here as a third piece. We omit it in this clean example.

Sheet Reconciliation
B2: Reconciliation — All Three Tie Out
B4: Enterprise Value by method
B5: Method 1 — FCFF / WACC | C5: =M1_WACC!$C$19 -> 7194.6224 | E5: Shield in the discount rate
B6: Method 2 — CCF / Ka | C6: =M2_CCF!$C$13 -> 7152.3609 | E6: Shield inside the cash flow
B7: Method 3 — APV (Vu + shield) | C7: =M3_APV!$C$23 -> 7165.4036 | E7: Shield as a separate line item
B9: Differences (should be ~0, tiny rounding only from TV conventions)
B10: CCF − WACC | C10: =M2_CCF!$C$13-M1_WACC!$C$19 -> -42.261562
B11: APV − CCF | C11: =M3_APV!$C$23-M2_CCF!$C$13 -> 13.042738
B13: WHY CCF ≈ APV (within rounding):
B14: Both discount operating cash at Ka. They differ ONLY in the shield's discount rate — APV uses Kd (6%), CCF effectively uses Ka (10%). With a fixed debt schedule, Kd is the more correct shield rate, so APV is marginally higher. Tiny gap = pure shield-rate choice.
B15: WHY WACC differs (~$40):
B16: WACC bakes in a CONSTANT 40% target D/V for years 1–5. But the actual debt deleverages 100%→0% of book. A single WACC cannot track a changing capital structure — THIS IS THE WHOLE POINT. For deleveraging firms, trust CCF / APV, not a single WACC.
B17: The takeaway:
B18: When leverage is stable → all three agree and WACC is easiest. When leverage changes (LBOs) → WACC drifts and is wrong; CCF and APV stay correct because they discount operations at the leverage-independent Ka.
B19: Debt = fixed $ schedule, want shield visible | C19: Use APV (shield at Kd, shown as its own number).
B20: Leverage scales with firm value | C20: Use CCF (shield at Ka, folded into cash flow).
