Workbook

Sheet Cost Classification
A1: Cost Classification of Harsh Electricals
B2: All the figures are in INR | D2: Traceability | F2: Behavioral | I2: Inventoriable/ Financial statement
A3: Cost | B3: Note | C3: Total Cost | D3: Direct | E3: Indirect | F3: Fixed | G3: Variable | H3: Mixed | I3: Product | J3: Period
A4: Salary of Nagesh | B4: Contractual Amount | C4: 600000 | E4: a | F4: a | I4: a
A5: Factory Rent | B5: 1050 sqft @8 per month | C5: =1050*8*12 -> 100800 | E5: a | F5: a | I5: a
A6: Office Rent | B6: 150 sqft @8 per month | C6: =150*8*12 -> 14400 | E6: a | F6: a | J6: a
A7: Raw Materials (Exhibit 4 of the case) | B7: 3260 Standard @1778 810 Baleno @2185 | C7: =(3260*1778)+(810*2185) -> 7566130 | D7: a | G7: a | I7: a
A8: Casual workers (for 3260 Standard and 810 Baleno) | B8: 1 hr for Standard@25/hr 1.2 hrs for Baleno@25/hr | C8: =(25*1*3260)+(25*1.2*810) -> 105800 | D8: a | G8: a | I8: a
A9: Indirect (Set-up) Labour | B9: 6 months@6000/month | C9: =6000*6 -> 36000 | E9: a | F9: a | I9: a
A10: Procurement Expenses | B10: 0.5% of raw materials | C10: =C7*0.005 -> 37830.65 | D10: a | G10: a | I10: a
A11: Drilling bit | B11: 10 per unit of cooler | C11: 40700 | D11: a | G11: a | I11: a
A12: Power Consumption | B12: 1 unit for Standard@10/unit 1.5 units for Baleno @10/unit | C12: =B25+B26 -> 44750 | D12: a | G12: a | I12: a
A13: Factory Electricity | B13: Actual during working and proportionate during off | C13: =B27+B28+B30 -> 71100 | D13: a | E13: a | H13: a | I13: a
A14: Office Electricity | C14: =B39 -> 16500 | E14: a | H14: a | J14: a
A15: Factory Insurance | B15: Contractual Amount | C15: 25000 | E15: a | F15: a | I15: a
A16: Consumables | C16: 45000 | E16: a | H16: a | I16: a
A17: Depreciation on Factory Machinery, Furnitures | B17: 300000 for 5 years and 40000 for 10 years | C17: =(300000/5)+(40000/10) -> 64000 | E17: a | F17: a | I17: a
A18: Depreciation on office equipment | B18: 80000 for 5 years and 60000 for 10 years | C18: =(60000/10)+(80000/5) -> 22000 | E18: a | F18: a | J18: a
A19: Selling Expenses | B19: 100 per unit of cooler sold | C19: 400000 | D19: a | G19: a | J19: a
A23: Workshop Electricity
A24: During the season
A25: Standard Coolers | B25: =3260*1*10 -> 32600 | C25: Direct
A26: Baleno Coolers | B26: =810*1.5*10 -> 12150 | C26: Direct
A27: Maintenance | B27: =10*6*10 -> 600 | C27: Indirect
A28: Factory Lighting | B28: =300*10*6 -> 18000 | C28: Indirect
A29: During off season
A30: Lighting & Maintenance | B30: =1000*10*6*7/8 -> 52500 | C30: Indirect
A31: Total | B31: =SUM(B25:B30) -> 115850
A33: Office Electricity
A34: During the season
A35: Office Computer | B35: =100*10*6 -> 6000 | C35: Indirect
A36: Office Lighting | B36: =50*10*6 -> 3000 | C36: Indirect
A37: During off season
A38: Office Lighting & Computer | B38: =1000*10*6*1/8 -> 7500 | C38: Indirect
A39: Total | B39: =SUM(B33:B38) -> 16500

Sheet Product Profitability
A1: Product Profitability Analysis
A2: Particulars | C2: Regular | D2: Baleno
A3: Direct materials consumed | B3: Total (INR)
A4: Body | C4: 650 | D4: 830
A5: Motor | C5: 500 | D5: 630
A6: Pump | C6: 90 | D6: 110
A7: Blade, clamp and wiring | C7: 168 | D7: 205
A8: Pipe, Water Distributor and Water Panel | C8: 190 | D8: 210
A9: Diverter | C9: 110 | D9: 110
A10: Packing (Carton & Labelling) | C10: 40 | D10: 50
A11: Wheel | C11: 30 | D11: 40
A12: Direct materials consumed | C12: =SUM(C4:C11) -> 1778 | D12: =SUM(D4:D11) -> 2185
A13: Direct Labour
A14: 5 labour | B14: 1hr @25/hr & 1.2 hrs@25/hr | C14: =1*25 -> 25 | D14: =1.2*25 -> 30
A15: Direct Expenses
A16: Procurement charges | C16: =C12*0.005 -> 8.89 | D16: =D12*0.005 -> 10.925
A17: Drilling bit | B17: INR 10/unit | C17: =10*1 -> 10 | D17: 10
A18: Power | C18: 10 | D18: 15
A19: Prime Cost | C19: =SUM(C12:C18) -> 1831.89 | D19: =SUM(D12:D18) -> 2250.925
A20: Manufacturing Overheads
A21: Supervisor's Salary (Nagesh) | B21: ='Cost Classification'!C4 -> 600000
A22: Consumables | B22: ='Cost Classification'!C16 -> 45000
A23: Rent (Factory) | B23: ='Cost Classification'!C5 -> 100800
A24: Depreciation (Factory) | B24: ='Cost Classification'!C17 -> 64000
A25: Factory Electricity | B25: ='Cost Classification'!B27+'Cost Classification'!B28+'Cost Classification'!B30 -> 71100
A26: Factory Insurance | B26: ='Cost Classification'!C15 -> 25000
A27: Indirect Labour | B27: ='Cost Classification'!C9 -> 36000
A28: Total Manufacturing Overheads | B28: =SUM(B21:B27) -> 941900
A29: Production of Standard Model | B29: =3200+60 -> 3260
A30: Production of Baleno Model | B30: =800+10 -> 810
A31: Total Direct Labour Cost | B31: =(B29*C14)+(B30*D14) -> 105800
A32: Cost Driver Rate/ Overhead Recovery Rate | B32: =B28/B31 -> 8.9026465
A33: Manufacturing Overheads | C33: =B32*C14 -> 222.56616 | D33: =B32*D14 -> 267.0794
A34: Product Cost | C34: =C19+C33 -> 2054.4562 | D34: =D19+D33 -> 2518.0044
A35: Revenue | C35: 2500 | D35: 3000
A36: Profit | C36: =C35-C34 -> 445.54384 | D36: =D35-D34 -> 481.9956
A37: Product Profitability (in %) | C37: =C36/C35 -> 0.17821753 | D37: =D36/D35 -> 0.1606652

Sheet COGS Statement
A1: Statement of Cost of goods Sold
A2: Particulars | B2: Amount (INR) | C2: Amount (INR)
A3: Opening inventory of Raw Material | B3: 0
A4: Add: Purchase of Raw Material 3260 standard@1778+810@2185 | B4: =('Product Profitability'!B29*'Product Profitability'!C12)+('Product Profitability'!B30*'Product Profitability'!D12) -> 7566130
A5: Less: Opening inventory of Raw Material | B5: 0
A6: Direct Material (Consumed) | C6: =B3+B4-B5 -> 7566130
A7: Direct Labour | C7: =('Product Profitability'!B29*'Product Profitability'!C14)+('Product Profitability'!B30*'Product Profitability'!D14) -> 105800
A8: Procurement Charges | C8: =C6*0.005 -> 37830.65
A9: Drilling Bits | C9: =('Product Profitability'!B29*'Product Profitability'!C17)+('Product Profitability'!B30*'Product Profitability'!D17) -> 40700
A10: Power Expenses | C10: ='Cost Classification'!B25+'Cost Classification'!B26 -> 44750
A11: Prime Cost | C11: =SUM(C6:C10) -> 7795210.7
A12: Manufacturing Overhead:
A13: Nagesh's Salary | B13: ='Product Profitability'!B21 -> 600000
A14: Consumables | B14: ='Product Profitability'!B22 -> 45000
A15: Rent (Factory) | B15: ='Product Profitability'!B23 -> 100800
A16: Depreciation | B16: ='Product Profitability'!B24 -> 64000
A17: Electricity | B17: ='Product Profitability'!B25 -> 71100
A18: Factory Insurance | B18: ='Product Profitability'!B26 -> 25000
A19: Indirect Labour | B19: ='Product Profitability'!B27 -> 36000 | C19: =SUM(B13:B19) -> 941900
A20: Cost of Production | C20: =C19+C11 -> 8737110.7
A21: Add Opening WIP | C21: 0
A22: Less Closing WIP | C22: 0
A23: Cost of goods Manufactured | C23: =C20 -> 8737110.7
A24: Add Opening Inventory of Finished Goods | C24: 0
A25: Less Closing Inventory of Finished Goods (60 Standard coolers@2054.46 and 10 Baleno@2518) | C25: =(60*'Product Profitability'!C34)+(10*'Product Profitability'!D34) -> 148447.41
A26: Cost of Goods Sold | C26: =C23-C25 -> 8588663.2

Sheet Projected Income Statement
A1: Projected Income Statement
A2: Particulars | C2: Amount (INR) | D2: Classification
A3: Revenue | C3: =(2500*3200)+(3000*800) -> 10400000
A4: COGS | C4: ='COGS Statement'!C26 -> 8588663.2 | D4: Product Cost
A5: Gross Profit | C5: =C3-C4 -> 1811336.8
A6: Operating Expenses | D6: Period cost
A7: Office Rent | B7: ='Cost Classification'!C6 -> 14400
A8: Office Electricity | B8: ='Cost Classification'!C14 -> 16500
A9: Selling & Distribution | B9: ='Cost Classification'!C19 -> 400000 | C9: =SUM(B7:B9) -> 430900
A10: EBITDA | C10: =C5-C9 -> 1380436.8
A11: Depreciation and Amortization on computer and furniture used for office | C11: ='Cost Classification'!C18 -> 22000 | D11: Period cost
A12: EBIT | C12: =C10-C11 -> 1358436.8
A13: Less: Interest | C13: 0 | D13: Period cost
A14: Add: Interest earned on bank deposit | C14: 8000
A15: Net Income/Profit before Tax | C15: =C12-C13+C14 -> 1366436.8
A16: Less: Tax | C16: =C15*12/100 -> 163972.41 | D16: Period cost
A17: Profit after Tax | C17: =C15-C16 -> 1202464.4

Sheet Variable Cost System
A1: Calculation of Profit in Variable/Marginal Cost System
A2: Particulars | B2: Normal | C2: Baleno | D2: Total
A3: Variable Costs
A4: Direct materials used | B4: ='Product Profitability'!C12 -> 1778 | C4: ='Product Profitability'!D12 -> 2185
A5: Direct Labour | B5: ='Product Profitability'!C14 -> 25 | C5: ='Product Profitability'!D14 -> 30
A6: Drilling bit | B6: ='Product Profitability'!C17 -> 10 | C6: ='Product Profitability'!D17 -> 10
A7: Distribution | B7: 100 | C7: 100
A8: Electricity | B8: 10 | C8: 15
A9: Procurement Cost | B9: =B4*0.005 -> 8.89 | C9: =C4*0.005 -> 10.925
A10: Per unit Var Cost | B10: =SUM(B4:B8) -> 1923 | C10: =SUM(C4:C8) -> 2340
A11: Selling Price | B11: 2500 | C11: 3000
A12: Contribution Per Unit | B12: =B11-B10 -> 577 | C12: =C11-C10 -> 660
A13: Units Sold | B13: 3200 | C13: 800
A14: Total Contribution | B14: =B12*B13 -> 1846400 | C14: =C12*C13 -> 528000 | D14: =B14+C14 -> 2374400
A15: Fixed Costs | D15: =B30 -> 994800
A16: EBIT | D16: =D14-D15 -> 1379600
A19: Total Fixed Costs
A20: Calculation of Fixed Costs
A21: Salary of Nagesh | B21: ='Cost Classification'!C4 -> 600000
A22: Factory Rent | B22: ='Cost Classification'!C5 -> 100800
A23: Office Rent | B23: ='Cost Classification'!C6 -> 14400
A24: Indirect Labour | B24: 36000
A25: Electricity | B25: ='Cost Classification'!B27+'Cost Classification'!B28+'Cost Classification'!B30+'Cost Classification'!B39 -> 87600
A26: Factory Insurance | B26: 25000
A27: Consumables | B27: ='Cost Classification'!C16 -> 45000
A28: Depreciation Workshop | B28: ='Product Profitability'!B24 -> 64000
A29: Dep on office equip. | B29: ='Projected Income Statement'!C11 -> 22000
A30: Total | B30: =SUM(B21:B29) -> 994800

Sheet BEP & Target Sales
A1: Calculation of Break Even Point
A2: Model | B2: Sales Mix | C2: Contribution | D2: Contribution of the Bundle
A3: Normal | B3: 4 | C3: ='Variable Cost System'!B12 -> 577 | D3: =C3*B3 -> 2308
A4: Baleno | B4: 1 | C4: ='Variable Cost System'!C12 -> 660 | D4: =C4*B4 -> 660
A5: Total | D5: =SUM(D3:D4) -> 2968
A6: Fixed Cost | D6: ='Variable Cost System'!D15 -> 994800
A7: BEP in bundles | B7: Fixes costs/Contribution | D7: =D6/D5 -> 335.1752
A8: BEP in units
A9: Normal | B9: 335*4 | D9: =D7*B3 -> 1340.7008
A10: Baleno | B10: 335*1 | D10: =D7*B4 -> 335.1752
A11: BEP in revenue
A12: Normal | B12: 1341 units@2500 | D12: =D9*2500 -> 3351752
A13: Baleno | B13: 335 Units@3000 | D13: =D10*3000 -> 1005525.6
A14: Total | B14: 1676 units | D14: =SUM(D12:D13) -> 4357277.6
A16: Sales required for Desired Profit
A17: Desired Profit (as in 2010-11) | B17: 859846
A18: Desired EBIT (as in 2010-11) | B18: 977780
A19: Desired Contribution | B19: =D6+B18 -> 1972580
A20: Reruired Sales in bundles | B20: =B19/D5 -> 664.6159
A21: Sales of Normal Model (in units) | B21: =B20*4 -> 2658.4636
A22: Sales of Baleno Model (in units) | B22: =B20*1 -> 664.6159
A23: Total Units | B23: =B21+B22 -> 3323.0795
A24: Sales of Normal Model (in Value) | B24: =B21*2500 -> 6646159
A25: Sales of Baleno Model (in Value) | B25: =B22*3000 -> 1993847.7
A26: Required Revenue for profit desired | B26: =B24+B25 -> 8640006.7
